CHANGELOG
LICENSE
MANIFEST.in
README.md
setup.cfg
setup.py
test.py
test2.py
Pylot.egg-info/PKG-INFO
Pylot.egg-info/SOURCES.txt
Pylot.egg-info/dependency_links.txt
Pylot.egg-info/entry_points.txt
Pylot.egg-info/not-zip-safe
Pylot.egg-info/pbr.json
Pylot.egg-info/requires.txt
Pylot.egg-info/top_level.txt
devtest/__init__.py
devtest/manage.py
devtest/run_hello.py
devtest/run_www.py
devtest/application/__init__.py
devtest/application/config.py
devtest/application/model.py
devtest/application/test.py
devtest/application/hello/__init__.py
devtest/application/hello/views.py
devtest/application/www/__init__.py
devtest/application/www/views.py
pylot/__init__.py
pylot/__init__.pyc
pylot/cmd.py
pylot/cmd.pyc
pylot/pkginfo.py
pylot/pkginfo.pyc
pylot/utils.py
pylot/utils.pyc
pylot/app_templates/__init__.py
pylot/app_templates/config.py
pylot/app_templates/deployapp.yml
pylot/app_templates/init.py
pylot/app_templates/manage.py
pylot/app_templates/model.py
pylot/app_templates/run.py
pylot/app_templates/admin/__init__.py
pylot/app_templates/admin/views.py
pylot/app_templates/admin/static/css/style.css
pylot/app_templates/admin/static/img/blank
pylot/app_templates/admin/static/js/app.js
pylot/app_templates/admin/static/vendor/bootstrap/css/bootstrap-theme.css
pylot/app_templates/admin/static/vendor/bootstrap/css/bootstrap-theme.css.map
pylot/app_templates/admin/static/vendor/bootstrap/css/bootstrap-theme.min.css
pylot/app_templates/admin/static/vendor/bootstrap/css/bootstrap.css
pylot/app_templates/admin/static/vendor/bootstrap/css/bootstrap.css.map
pylot/app_templates/admin/static/vendor/bootstrap/css/bootstrap.min.css
pylot/app_templates/admin/static/vendor/bootstrap/fonts/glyphicons-halflings-regular.eot
pylot/app_templates/admin/static/vendor/bootstrap/fonts/glyphicons-halflings-regular.svg
pylot/app_templates/admin/static/vendor/bootstrap/fonts/glyphicons-halflings-regular.ttf
pylot/app_templates/admin/static/vendor/bootstrap/fonts/glyphicons-halflings-regular.woff
pylot/app_templates/admin/static/vendor/bootstrap/js/bootstrap.js
pylot/app_templates/admin/static/vendor/bootstrap/js/bootstrap.min.js
pylot/app_templates/admin/static/vendor/bootswatch/README
